ppgames/__init__.py
ppgames/game.py
ppgames-0.1.8.dist-info/METADATA
ppgames-0.1.8.dist-info/WHEEL
ppgames-0.1.8.dist-info/entry_points.txt
ppgames-0.1.8.dist-info/top_level.txt
ppgames-0.1.8.dist-info/RECORD
