Metadata-Version: 2.1
Name: ppgames
Version: 0.1.8
Summary: A simple game designed by PythonPavan
Home-page: https://github.com/pythonpavan04/ppgames
Author: PYTHON PAVAN
Author-email: pavan.sidd2004@gmail.com
Classifier: Programming Language :: Python :: 3
Classifier: License :: OSI Approved :: MIT License
Classifier: Operating System :: OS Independent
